creatree/__init__.py
creatree/cli.py
creatree/config.py
creatree/core.py
creatree/utils.py
creatree-0.1.3.dist-info/LICENSE
creatree-0.1.3.dist-info/METADATA
creatree-0.1.3.dist-info/WHEEL
creatree-0.1.3.dist-info/entry_points.txt
creatree-0.1.3.dist-info/top_level.txt
creatree-0.1.3.dist-info/RECORD
