Metadata-Version: 2.2
Name: creatree
Version: 0.1.3
Summary: A CLI tool and library to create directory trees from tree strings.
Author-email: Subhayu Kumar Bala <balasubhayu99@gmail.com>
License: MIT License
Project-URL: Homepage, https://github.com/subhayu99/creatree
Project-URL: Bug Tracker, https://github.com/subhayu99/creatree/issues
Keywords: directory,tree,filesystem,cli
Classifier: Development Status :: 4 - Beta
Classifier: Intended Audience :: Developers
Classifier: License :: OSI Approved :: MIT License
Classifier: Programming Language :: Python :: 3
Classifier: Programming Language :: Python :: 3.7
Classifier: Programming Language :: Python :: 3.8
Classifier: Programming Language :: Python :: 3.9
Classifier: Programming Language :: Python :: 3.10
Requires-Python: >=3.10
License-File: LICENSE
